cryptoaddress/__init__.py
cryptoaddress/core.py
cryptoaddress/utils.py
cryptoaddress-0.2.1.dist-info/LICENSE
cryptoaddress-0.2.1.dist-info/METADATA
cryptoaddress-0.2.1.dist-info/WHEEL
cryptoaddress-0.2.1.dist-info/top_level.txt
cryptoaddress-0.2.1.dist-info/RECORD
