Metadata-Version: 2.1
Name: cryptoaddress
Version: 0.2.1
Summary: Python library to verify crypto addresses.
Home-page: UNKNOWN
Author: Jose Molina Colmenero
Author-email: molina@bity.com
License: MIT
Platform: UNKNOWN
Classifier: Development Status :: 5 - Production/Stable
Classifier: Intended Audience :: Developers
Classifier: Intended Audience :: Financial and Insurance Industry
Classifier: License :: OSI Approved :: MIT License
Classifier: Operating System :: OS Independent
Classifier: Programming Language :: Python :: 3.5
Classifier: Topic :: Software Development :: Libraries :: Python Modules
Requires-Dist: pysha3
